{
  "fio version" : "fio-3.12",
  "timestamp" : 1542281204,
  "timestamp_ms" : 1542281204473,
  "time" : "Thu Nov 15 12:26:44 2018",
  "global options" : {
    "direct" : "1",
    "ioengine" : "libaio",
    "size" : "5G",
    "filesize" : "5G",
    "iodepth" : "10",
    "runtime" : "1m",
    "filename" : "randread-raw-data-5G"
  },
  "jobs" : [
    {
      "jobname" : "randread-128k-256k",
      "groupid" : 0,
      "error" : 0,
      "eta" : 0,
      "elapsed" : 61,
      "job options" : {
        "rw" : "randread",
        "bsrange" : "128k-256k"
      },
      "read" : {
        "io_bytes" : 350486528,
        "io_kbytes" : 342272,
        "bw_bytes" : 5831334,
        "bw" : 5694,
        "iops" : 30.347398,
        "runtime" : 60104,
        "total_ios" : 1824,
        "short_ios" : 0,
        "drop_ios" : 0,
        "slat_ns" : {
          "min" : 14876,
          "max" : 286096577,
          "mean" : 1261788.010417,
          "stddev" : 15690077.059607
        },
        "clat_ns" : {
          "min" : 34841372,
          "max" : 4082004283,
          "mean" : 328172646.748355,
          "stddev" : 286467482.539951,
          "percentile" : {
            "1.000000" : 124256256,
            "5.000000" : 204472320,
            "10.000000" : 229638144,
            "20.000000" : 256901120,
            "30.000000" : 274726912,
            "40.000000" : 287309824,
            "50.000000" : 299892736,
            "60.000000" : 312475648,
            "70.000000" : 333447168,
            "80.000000" : 350224384,
            "90.000000" : 392167424,
            "95.000000" : 438304768,
            "99.000000" : 851443712,
            "99.500000" : 3909091328,
            "99.900000" : 4076863488,
            "99.950000" : 4076863488,
            "99.990000" : 4076863488
          }
        },
        "lat_ns" : {
          "min" : 36012820,
          "max" : 4082048143,
          "mean" : 329436266.909539,
          "stddev" : 286260019.221011
        },
        "bw_min" : 3328,
        "bw_max" : 8448,
        "bw_agg" : 11.734820,
        "bw_mean" : 6075.116071,
        "bw_dev" : 1128.337234,
        "bw_samples" : 112,
        "iops_min" : 20,
        "iops_max" : 46,
        "iops_mean" : 32.366071,
        "iops_stddev" : 6.017984,
        "iops_samples" : 112
      },
      "write" : {
        "io_bytes" : 0,
        "io_kbytes" : 0,
        "bw_bytes" : 0,
        "bw" : 0,
        "iops" : 0.000000,
        "runtime" : 0,
        "total_ios" : 0,
        "short_ios" : 0,
        "drop_ios" : 0,
        "slat_ns" : {
          "min" : 0,
          "max" : 0,
          "mean" : 0.000000,
          "stddev" : 0.000000
        },
        "clat_ns" : {
          "min" : 0,
          "max" : 0,
          "mean" : 0.000000,
          "stddev" : 0.000000,
          "percentile" : {
            "1.000000" : 0,
            "5.000000" : 0,
            "10.000000" : 0,
            "20.000000" : 0,
            "30.000000" : 0,
            "40.000000" : 0,
            "50.000000" : 0,
            "60.000000" : 0,
            "70.000000" : 0,
            "80.000000" : 0,
            "90.000000" : 0,
            "95.000000" : 0,
            "99.000000" : 0,
            "99.500000" : 0,
            "99.900000" : 0,
            "99.950000" : 0,
            "99.990000" : 0
          }
        },
        "lat_ns" : {
          "min" : 0,
          "max" : 0,
          "mean" : 0.000000,
          "stddev" : 0.000000
        },
        "bw_min" : 0,
        "bw_max" : 0,
        "bw_agg" : 0.000000,
        "bw_mean" : 0.000000,
        "bw_dev" : 0.000000,
        "bw_samples" : 0,
        "iops_min" : 0,
        "iops_max" : 0,
        "iops_mean" : 0.000000,
        "iops_stddev" : 0.000000,
        "iops_samples" : 0
      },
      "trim" : {
        "io_bytes" : 0,
        "io_kbytes" : 0,
        "bw_bytes" : 0,
        "bw" : 0,
        "iops" : 0.000000,
        "runtime" : 0,
        "total_ios" : 0,
        "short_ios" : 0,
        "drop_ios" : 0,
        "slat_ns" : {
          "min" : 0,
          "max" : 0,
          "mean" : 0.000000,
          "stddev" : 0.000000
        },
        "clat_ns" : {
          "min" : 0,
          "max" : 0,
          "mean" : 0.000000,
          "stddev" : 0.000000,
          "percentile" : {
            "1.000000" : 0,
            "5.000000" : 0,
            "10.000000" : 0,
            "20.000000" : 0,
            "30.000000" : 0,
            "40.000000" : 0,
            "50.000000" : 0,
            "60.000000" : 0,
            "70.000000" : 0,
            "80.000000" : 0,
            "90.000000" : 0,
            "95.000000" : 0,
            "99.000000" : 0,
            "99.500000" : 0,
            "99.900000" : 0,
            "99.950000" : 0,
            "99.990000" : 0
          }
        },
        "lat_ns" : {
          "min" : 0,
          "max" : 0,
          "mean" : 0.000000,
          "stddev" : 0.000000
        },
        "bw_min" : 0,
        "bw_max" : 0,
        "bw_agg" : 0.000000,
        "bw_mean" : 0.000000,
        "bw_dev" : 0.000000,
        "bw_samples" : 0,
        "iops_min" : 0,
        "iops_max" : 0,
        "iops_mean" : 0.000000,
        "iops_stddev" : 0.000000,
        "iops_samples" : 0
      },
      "sync" : {
        "lat_ns" : {
          "min" : 0,
          "max" : 0,
          "mean" : 0.000000,
          "stddev" : 0.000000,
          "percentile" : {
            "1.000000" : 0,
            "5.000000" : 0,
            "10.000000" : 0,
            "20.000000" : 0,
            "30.000000" : 0,
            "40.000000" : 0,
            "50.000000" : 0,
            "60.000000" : 0,
            "70.000000" : 0,
            "80.000000" : 0,
            "90.000000" : 0,
            "95.000000" : 0,
            "99.000000" : 0,
            "99.500000" : 0,
            "99.900000" : 0,
            "99.950000" : 0,
            "99.990000" : 0
          }
        },
        "total_ios" : 0
      },
      "job_runtime" : 60103,
      "usr_cpu" : 0.053242,
      "sys_cpu" : 0.193002,
      "ctx" : 1884,
      "majf" : 0,
      "minf" : 651,
      "iodepth_level" : {
        "1" : 0.100000,
        "2" : 0.109649,
        "4" : 0.219298,
        "8" : 99.616228,
        "16" : 0.000000,
        "32" : 0.000000,
        ">=64" : 0.000000
      },
      "iodepth_submit" : {
        "0" : 0.000000,
        "4" : 100.000000,
        "8" : 0.000000,
        "16" : 0.000000,
        "32" : 0.000000,
        "64" : 0.000000,
        ">=64" : 0.000000
      },
      "iodepth_complete" : {
        "0" : 0.000000,
        "4" : 99.944934,
        "8" : 0.000000,
        "16" : 0.100000,
        "32" : 0.000000,
        "64" : 0.000000,
        ">=64" : 0.000000
      },
      "latency_ns" : {
        "2" : 0.000000,
        "4" : 0.000000,
        "10" : 0.000000,
        "20" : 0.000000,
        "50" : 0.000000,
        "100" : 0.000000,
        "250" : 0.000000,
        "500" : 0.000000,
        "750" : 0.000000,
        "1000" : 0.000000
      },
      "latency_us" : {
        "2" : 0.000000,
        "4" : 0.000000,
        "10" : 0.000000,
        "20" : 0.000000,
        "50" : 0.000000,
        "100" : 0.000000,
        "250" : 0.000000,
        "500" : 0.000000,
        "750" : 0.000000,
        "1000" : 0.000000
      },
      "latency_ms" : {
        "2" : 0.000000,
        "4" : 0.000000,
        "10" : 0.000000,
        "20" : 0.000000,
        "50" : 0.109649,
        "100" : 0.438596,
        "250" : 15.789474,
        "500" : 81.085526,
        "750" : 1.480263,
        "1000" : 0.548246,
        "2000" : 0.000000,
        ">=2000" : 0.000000
      },
      "latency_depth" : 10,
      "latency_target" : 0,
      "latency_percentile" : 100.000000,
      "latency_window" : 0
    },
    {
      "jobname" : "seqread",
      "groupid" : 0,
      "error" : 0,
      "eta" : 0,
      "elapsed" : 61,
      "job options" : {
        "rw" : "read",
        "bs" : "1m"
      },
      "read" : {
        "io_bytes" : 2843738112,
        "io_kbytes" : 2777088,
        "bw_bytes" : 47195839,
        "bw" : 46089,
        "iops" : 45.009460,
        "runtime" : 60254,
        "total_ios" : 2712,
        "short_ios" : 0,
        "drop_ios" : 0,
        "slat_ns" : {
          "min" : 55035,
          "max" : 388825702,
          "mean" : 1066783.333702,
          "stddev" : 15083638.865177
        },
        "clat_ns" : {
          "min" : 144851,
          "max" : 4059522653,
          "mean" : 220992342.783186,
          "stddev" : 230217670.954800,
          "percentile" : {
            "1.000000" : 17170432,
            "5.000000" : 22413312,
            "10.000000" : 23199744,
            "20.000000" : 30015488,
            "30.000000" : 179306496,
            "40.000000" : 238026752,
            "50.000000" : 254803968,
            "60.000000" : 267386880,
            "70.000000" : 283115520,
            "80.000000" : 304087040,
            "90.000000" : 329252864,
            "95.000000" : 358612992,
            "99.000000" : 476053504,
            "99.500000" : 851443712,
            "99.900000" : 4043309056,
            "99.950000" : 4043309056,
            "99.990000" : 4043309056
          }
        },
        "lat_ns" : {
          "min" : 2203283,
          "max" : 4059621478,
          "mean" : 222060998.391962,
          "stddev" : 230183387.622648
        },
        "bw_min" : 22528,
        "bw_max" : 133120,
        "bw_agg" : 89.070053,
        "bw_mean" : 46111.566667,
        "bw_dev" : 21208.002566,
        "bw_samples" : 120,
        "iops_min" : 22,
        "iops_max" : 130,
        "iops_mean" : 45.000000,
        "iops_stddev" : 20.723064,
        "iops_samples" : 120
      },
      "write" : {
        "io_bytes" : 0,
        "io_kbytes" : 0,
        "bw_bytes" : 0,
        "bw" : 0,
        "iops" : 0.000000,
        "runtime" : 0,
        "total_ios" : 0,
        "short_ios" : 0,
        "drop_ios" : 0,
        "slat_ns" : {
          "min" : 0,
          "max" : 0,
          "mean" : 0.000000,
          "stddev" : 0.000000
        },
        "clat_ns" : {
          "min" : 0,
          "max" : 0,
          "mean" : 0.000000,
          "stddev" : 0.000000,
          "percentile" : {
            "1.000000" : 0,
            "5.000000" : 0,
            "10.000000" : 0,
            "20.000000" : 0,
            "30.000000" : 0,
            "40.000000" : 0,
            "50.000000" : 0,
            "60.000000" : 0,
            "70.000000" : 0,
            "80.000000" : 0,
            "90.000000" : 0,
            "95.000000" : 0,
            "99.000000" : 0,
            "99.500000" : 0,
            "99.900000" : 0,
            "99.950000" : 0,
            "99.990000" : 0
          }
        },
        "lat_ns" : {
          "min" : 0,
          "max" : 0,
          "mean" : 0.000000,
          "stddev" : 0.000000
        },
        "bw_min" : 0,
        "bw_max" : 0,
        "bw_agg" : 0.000000,
        "bw_mean" : 0.000000,
        "bw_dev" : 0.000000,
        "bw_samples" : 0,
        "iops_min" : 0,
        "iops_max" : 0,
        "iops_mean" : 0.000000,
        "iops_stddev" : 0.000000,
        "iops_samples" : 0
      },
      "trim" : {
        "io_bytes" : 0,
        "io_kbytes" : 0,
        "bw_bytes" : 0,
        "bw" : 0,
        "iops" : 0.000000,
        "runtime" : 0,
        "total_ios" : 0,
        "short_ios" : 0,
        "drop_ios" : 0,
        "slat_ns" : {
          "min" : 0,
          "max" : 0,
          "mean" : 0.000000,
          "stddev" : 0.000000
        },
        "clat_ns" : {
          "min" : 0,
          "max" : 0,
          "mean" : 0.000000,
          "stddev" : 0.000000,
          "percentile" : {
            "1.000000" : 0,
            "5.000000" : 0,
            "10.000000" : 0,
            "20.000000" : 0,
            "30.000000" : 0,
            "40.000000" : 0,
            "50.000000" : 0,
            "60.000000" : 0,
            "70.000000" : 0,
            "80.000000" : 0,
            "90.000000" : 0,
            "95.000000" : 0,
            "99.000000" : 0,
            "99.500000" : 0,
            "99.900000" : 0,
            "99.950000" : 0,
            "99.990000" : 0
          }
        },
        "lat_ns" : {
          "min" : 0,
          "max" : 0,
          "mean" : 0.000000,
          "stddev" : 0.000000
        },
        "bw_min" : 0,
        "bw_max" : 0,
        "bw_agg" : 0.000000,
        "bw_mean" : 0.000000,
        "bw_dev" : 0.000000,
        "bw_samples" : 0,
        "iops_min" : 0,
        "iops_max" : 0,
        "iops_mean" : 0.000000,
        "iops_stddev" : 0.000000,
        "iops_samples" : 0
      },
      "sync" : {
        "lat_ns" : {
          "min" : 0,
          "max" : 0,
          "mean" : 0.000000,
          "stddev" : 0.000000,
          "percentile" : {
            "1.000000" : 0,
            "5.000000" : 0,
            "10.000000" : 0,
            "20.000000" : 0,
            "30.000000" : 0,
            "40.000000" : 0,
            "50.000000" : 0,
            "60.000000" : 0,
            "70.000000" : 0,
            "80.000000" : 0,
            "90.000000" : 0,
            "95.000000" : 0,
            "99.000000" : 0,
            "99.500000" : 0,
            "99.900000" : 0,
            "99.950000" : 0,
            "99.990000" : 0
          }
        },
        "total_ios" : 0
      },
      "job_runtime" : 60253,
      "usr_cpu" : 0.039832,
      "sys_cpu" : 0.617397,
      "ctx" : 2601,
      "majf" : 0,
      "minf" : 2571,
      "iodepth_level" : {
        "1" : 0.100000,
        "2" : 0.100000,
        "4" : 0.147493,
        "8" : 99.741888,
        "16" : 0.000000,
        "32" : 0.000000,
        ">=64" : 0.000000
      },
      "iodepth_submit" : {
        "0" : 0.000000,
        "4" : 100.000000,
        "8" : 0.000000,
        "16" : 0.000000,
        "32" : 0.000000,
        "64" : 0.000000,
        ">=64" : 0.000000
      },
      "iodepth_complete" : {
        "0" : 0.000000,
        "4" : 99.963018,
        "8" : 0.000000,
        "16" : 0.100000,
        "32" : 0.000000,
        "64" : 0.000000,
        ">=64" : 0.000000
      },
      "latency_ns" : {
        "2" : 0.000000,
        "4" : 0.000000,
        "10" : 0.000000,
        "20" : 0.000000,
        "50" : 0.000000,
        "100" : 0.000000,
        "250" : 0.000000,
        "500" : 0.000000,
        "750" : 0.000000,
        "1000" : 0.000000
      },
      "latency_us" : {
        "2" : 0.000000,
        "4" : 0.000000,
        "10" : 0.000000,
        "20" : 0.000000,
        "50" : 0.000000,
        "100" : 0.000000,
        "250" : 0.036873,
        "500" : 0.000000,
        "750" : 0.000000,
        "1000" : 0.000000
      },
      "latency_ms" : {
        "2" : 0.036873,
        "4" : 0.110619,
        "10" : 0.294985,
        "20" : 0.626844,
        "50" : 24.225664,
        "100" : 1.364307,
        "250" : 21.238938,
        "500" : 51.401180,
        "750" : 0.110619,
        "1000" : 0.258112,
        "2000" : 0.000000,
        ">=2000" : 0.000000
      },
      "latency_depth" : 10,
      "latency_target" : 0,
      "latency_percentile" : 100.000000,
      "latency_window" : 0
    },
    {
      "jobname" : "seqwrite",
      "groupid" : 0,
      "error" : 0,
      "eta" : 0,
      "elapsed" : 61,
      "job options" : {
        "rw" : "write",
        "bs" : "1m"
      },
      "read" : {
        "io_bytes" : 0,
        "io_kbytes" : 0,
        "bw_bytes" : 0,
        "bw" : 0,
        "iops" : 0.000000,
        "runtime" : 0,
        "total_ios" : 0,
        "short_ios" : 0,
        "drop_ios" : 0,
        "slat_ns" : {
          "min" : 0,
          "max" : 0,
          "mean" : 0.000000,
          "stddev" : 0.000000
        },
        "clat_ns" : {
          "min" : 0,
          "max" : 0,
          "mean" : 0.000000,
          "stddev" : 0.000000,
          "percentile" : {
            "1.000000" : 0,
            "5.000000" : 0,
            "10.000000" : 0,
            "20.000000" : 0,
            "30.000000" : 0,
            "40.000000" : 0,
            "50.000000" : 0,
            "60.000000" : 0,
            "70.000000" : 0,
            "80.000000" : 0,
            "90.000000" : 0,
            "95.000000" : 0,
            "99.000000" : 0,
            "99.500000" : 0,
            "99.900000" : 0,
            "99.950000" : 0,
            "99.990000" : 0
          }
        },
        "lat_ns" : {
          "min" : 0,
          "max" : 0,
          "mean" : 0.000000,
          "stddev" : 0.000000
        },
        "bw_min" : 0,
        "bw_max" : 0,
        "bw_agg" : 0.000000,
        "bw_mean" : 0.000000,
        "bw_dev" : 0.000000,
        "bw_samples" : 0,
        "iops_min" : 0,
        "iops_max" : 0,
        "iops_mean" : 0.000000,
        "iops_stddev" : 0.000000,
        "iops_samples" : 0
      },
      "write" : {
        "io_bytes" : 2148532224,
        "io_kbytes" : 2098176,
        "bw_bytes" : 35660285,
        "bw" : 34824,
        "iops" : 34.008299,
        "runtime" : 60250,
        "total_ios" : 2049,
        "short_ios" : 0,
        "drop_ios" : 0,
        "slat_ns" : {
          "min" : 61390,
          "max" : 270737012,
          "mean" : 1395828.389458,
          "stddev" : 17019358.782073
        },
        "clat_ns" : {
          "min" : 95491543,
          "max" : 4156400964,
          "mean" : 292512560.198146,
          "stddev" : 261444360.973913,
          "percentile" : {
            "1.000000" : 133693440,
            "5.000000" : 189792256,
            "10.000000" : 214958080,
            "20.000000" : 235929600,
            "30.000000" : 248512512,
            "40.000000" : 256901120,
            "50.000000" : 265289728,
            "60.000000" : 274726912,
            "70.000000" : 287309824,
            "80.000000" : 304087040,
            "90.000000" : 337641472,
            "95.000000" : 413138944,
            "99.000000" : 583008256,
            "99.500000" : 994050048,
            "99.900000" : 3942645760,
            "99.950000" : 4143972352,
            "99.990000" : 4143972352
          }
        },
        "lat_ns" : {
          "min" : 95626057,
          "max" : 4156522488,
          "mean" : 293910281.284041,
          "stddev" : 261568592.854344
        },
        "bw_min" : 2048,
        "bw_max" : 53248,
        "bw_agg" : 100.000000,
        "bw_mean" : 36624.552632,
        "bw_dev" : 7345.733650,
        "bw_samples" : 114,
        "iops_min" : 2,
        "iops_max" : 52,
        "iops_mean" : 35.701754,
        "iops_stddev" : 7.130800,
        "iops_samples" : 114
      },
      "trim" : {
        "io_bytes" : 0,
        "io_kbytes" : 0,
        "bw_bytes" : 0,
        "bw" : 0,
        "iops" : 0.000000,
        "runtime" : 0,
        "total_ios" : 0,
        "short_ios" : 0,
        "drop_ios" : 0,
        "slat_ns" : {
          "min" : 0,
          "max" : 0,
          "mean" : 0.000000,
          "stddev" : 0.000000
        },
        "clat_ns" : {
          "min" : 0,
          "max" : 0,
          "mean" : 0.000000,
          "stddev" : 0.000000,
          "percentile" : {
            "1.000000" : 0,
            "5.000000" : 0,
            "10.000000" : 0,
            "20.000000" : 0,
            "30.000000" : 0,
            "40.000000" : 0,
            "50.000000" : 0,
            "60.000000" : 0,
            "70.000000" : 0,
            "80.000000" : 0,
            "90.000000" : 0,
            "95.000000" : 0,
            "99.000000" : 0,
            "99.500000" : 0,
            "99.900000" : 0,
            "99.950000" : 0,
            "99.990000" : 0
          }
        },
        "lat_ns" : {
          "min" : 0,
          "max" : 0,
          "mean" : 0.000000,
          "stddev" : 0.000000
        },
        "bw_min" : 0,
        "bw_max" : 0,
        "bw_agg" : 0.000000,
        "bw_mean" : 0.000000,
        "bw_dev" : 0.000000,
        "bw_samples" : 0,
        "iops_min" : 0,
        "iops_max" : 0,
        "iops_mean" : 0.000000,
        "iops_stddev" : 0.000000,
        "iops_samples" : 0
      },
      "sync" : {
        "lat_ns" : {
          "min" : 0,
          "max" : 0,
          "mean" : 0.000000,
          "stddev" : 0.000000,
          "percentile" : {
            "1.000000" : 0,
            "5.000000" : 0,
            "10.000000" : 0,
            "20.000000" : 0,
            "30.000000" : 0,
            "40.000000" : 0,
            "50.000000" : 0,
            "60.000000" : 0,
            "70.000000" : 0,
            "80.000000" : 0,
            "90.000000" : 0,
            "95.000000" : 0,
            "99.000000" : 0,
            "99.500000" : 0,
            "99.900000" : 0,
            "99.950000" : 0,
            "99.990000" : 0
          }
        },
        "total_ios" : 0
      },
      "job_runtime" : 60249,
      "usr_cpu" : 0.185895,
      "sys_cpu" : 0.358512,
      "ctx" : 1815,
      "majf" : 0,
      "minf" : 12,
      "iodepth_level" : {
        "1" : 0.100000,
        "2" : 0.100000,
        "4" : 0.195217,
        "8" : 99.658370,
        "16" : 0.000000,
        "32" : 0.000000,
        ">=64" : 0.000000
      },
      "iodepth_submit" : {
        "0" : 0.000000,
        "4" : 100.000000,
        "8" : 0.000000,
        "16" : 0.000000,
        "32" : 0.000000,
        "64" : 0.000000,
        ">=64" : 0.000000
      },
      "iodepth_complete" : {
        "0" : 0.000000,
        "4" : 99.951004,
        "8" : 0.000000,
        "16" : 0.100000,
        "32" : 0.000000,
        "64" : 0.000000,
        ">=64" : 0.000000
      },
      "latency_ns" : {
        "2" : 0.000000,
        "4" : 0.000000,
        "10" : 0.000000,
        "20" : 0.000000,
        "50" : 0.000000,
        "100" : 0.000000,
        "250" : 0.000000,
        "500" : 0.000000,
        "750" : 0.000000,
        "1000" : 0.000000
      },
      "latency_us" : {
        "2" : 0.000000,
        "4" : 0.000000,
        "10" : 0.000000,
        "20" : 0.000000,
        "50" : 0.000000,
        "100" : 0.000000,
        "250" : 0.000000,
        "500" : 0.000000,
        "750" : 0.000000,
        "1000" : 0.000000
      },
      "latency_ms" : {
        "2" : 0.000000,
        "4" : 0.000000,
        "10" : 0.000000,
        "20" : 0.000000,
        "50" : 0.000000,
        "100" : 0.341630,
        "250" : 32.113226,
        "500" : 66.129819,
        "750" : 0.439239,
        "1000" : 0.488043,
        "2000" : 0.000000,
        ">=2000" : 0.000000
      },
      "latency_depth" : 10,
      "latency_target" : 0,
      "latency_percentile" : 100.000000,
      "latency_window" : 0
    }
  ],
  "disk_util" : [
    {
      "name" : "sdb",
      "read_ios" : 5058,
      "write_ios" : 2337,
      "read_merges" : 43,
      "write_merges" : 194,
      "read_ticks" : 1259580,
      "write_ticks" : 665464,
      "in_queue" : 1926860,
      "util" : 99.905323
    }
  ]
}
