{
  "fio version" : "fio-3.12",
  "timestamp" : 1542277775,
  "timestamp_ms" : 1542277775858,
  "time" : "Thu Nov 15 11:29:35 2018",
  "global options" : {
    "direct" : "1",
    "ioengine" : "libaio",
    "size" : "5G",
    "filesize" : "5G",
    "iodepth" : "10",
    "runtime" : "1m",
    "filename" : "randread-raw-data-5G"
  },
  "jobs" : [
    {
      "jobname" : "randread-1k-4k",
      "groupid" : 0,
      "error" : 0,
      "eta" : 0,
      "elapsed" : 61,
      "job options" : {
        "rw" : "randread",
        "bsrange" : "1k-4k"
      },
      "read" : {
        "io_bytes" : 7025581056,
        "io_kbytes" : 6860919,
        "bw_bytes" : 117091066,
        "bw" : 114346,
        "iops" : 54252.162464,
        "runtime" : 60001,
        "total_ios" : 3255184,
        "short_ios" : 0,
        "drop_ios" : 0,
        "slat_ns" : {
          "min" : 2234,
          "max" : 665308,
          "mean" : 4535.855004,
          "stddev" : 4352.935866
        },
        "clat_ns" : {
          "min" : 19695,
          "max" : 20697465,
          "mean" : 174922.299246,
          "stddev" : 367186.594407,
          "percentile" : {
            "1.000000" : 59648,
            "5.000000" : 72192,
            "10.000000" : 78336,
            "20.000000" : 87552,
            "30.000000" : 94720,
            "40.000000" : 101888,
            "50.000000" : 110080,
            "60.000000" : 119296,
            "70.000000" : 129536,
            "80.000000" : 144384,
            "90.000000" : 171008,
            "95.000000" : 238592,
            "99.000000" : 2473984,
            "99.500000" : 2834432,
            "99.900000" : 3915776,
            "99.950000" : 4816896,
            "99.990000" : 6717440
          }
        },
        "lat_ns" : {
          "min" : 23536,
          "max" : 20726658,
          "mean" : 180621.459114,
          "stddev" : 367352.590829
        },
        "bw_min" : 87628,
        "bw_max" : 161964,
        "bw_agg" : 58.133424,
        "bw_mean" : 114101.378151,
        "bw_dev" : 14515.591091,
        "bw_samples" : 119,
        "iops_min" : 37516,
        "iops_max" : 67514,
        "iops_mean" : 54160.605042,
        "iops_stddev" : 6892.527751,
        "iops_samples" : 119
      },
      "write" : {
        "io_bytes" : 0,
        "io_kbytes" : 0,
        "bw_bytes" : 0,
        "bw" : 0,
        "iops" : 0.000000,
        "runtime" : 0,
        "total_ios" : 0,
        "short_ios" : 0,
        "drop_ios" : 0,
        "slat_ns" : {
          "min" : 0,
          "max" : 0,
          "mean" : 0.000000,
          "stddev" : 0.000000
        },
        "clat_ns" : {
          "min" : 0,
          "max" : 0,
          "mean" : 0.000000,
          "stddev" : 0.000000,
          "percentile" : {
            "1.000000" : 0,
            "5.000000" : 0,
            "10.000000" : 0,
            "20.000000" : 0,
            "30.000000" : 0,
            "40.000000" : 0,
            "50.000000" : 0,
            "60.000000" : 0,
            "70.000000" : 0,
            "80.000000" : 0,
            "90.000000" : 0,
            "95.000000" : 0,
            "99.000000" : 0,
            "99.500000" : 0,
            "99.900000" : 0,
            "99.950000" : 0,
            "99.990000" : 0
          }
        },
        "lat_ns" : {
          "min" : 0,
          "max" : 0,
          "mean" : 0.000000,
          "stddev" : 0.000000
        },
        "bw_min" : 0,
        "bw_max" : 0,
        "bw_agg" : 0.000000,
        "bw_mean" : 0.000000,
        "bw_dev" : 0.000000,
        "bw_samples" : 0,
        "iops_min" : 0,
        "iops_max" : 0,
        "iops_mean" : 0.000000,
        "iops_stddev" : 0.000000,
        "iops_samples" : 0
      },
      "trim" : {
        "io_bytes" : 0,
        "io_kbytes" : 0,
        "bw_bytes" : 0,
        "bw" : 0,
        "iops" : 0.000000,
        "runtime" : 0,
        "total_ios" : 0,
        "short_ios" : 0,
        "drop_ios" : 0,
        "slat_ns" : {
          "min" : 0,
          "max" : 0,
          "mean" : 0.000000,
          "stddev" : 0.000000
        },
        "clat_ns" : {
          "min" : 0,
          "max" : 0,
          "mean" : 0.000000,
          "stddev" : 0.000000,
          "percentile" : {
            "1.000000" : 0,
            "5.000000" : 0,
            "10.000000" : 0,
            "20.000000" : 0,
            "30.000000" : 0,
            "40.000000" : 0,
            "50.000000" : 0,
            "60.000000" : 0,
            "70.000000" : 0,
            "80.000000" : 0,
            "90.000000" : 0,
            "95.000000" : 0,
            "99.000000" : 0,
            "99.500000" : 0,
            "99.900000" : 0,
            "99.950000" : 0,
            "99.990000" : 0
          }
        },
        "lat_ns" : {
          "min" : 0,
          "max" : 0,
          "mean" : 0.000000,
          "stddev" : 0.000000
        },
        "bw_min" : 0,
        "bw_max" : 0,
        "bw_agg" : 0.000000,
        "bw_mean" : 0.000000,
        "bw_dev" : 0.000000,
        "bw_samples" : 0,
        "iops_min" : 0,
        "iops_max" : 0,
        "iops_mean" : 0.000000,
        "iops_stddev" : 0.000000,
        "iops_samples" : 0
      },
      "sync" : {
        "lat_ns" : {
          "min" : 0,
          "max" : 0,
          "mean" : 0.000000,
          "stddev" : 0.000000,
          "percentile" : {
            "1.000000" : 0,
            "5.000000" : 0,
            "10.000000" : 0,
            "20.000000" : 0,
            "30.000000" : 0,
            "40.000000" : 0,
            "50.000000" : 0,
            "60.000000" : 0,
            "70.000000" : 0,
            "80.000000" : 0,
            "90.000000" : 0,
            "95.000000" : 0,
            "99.000000" : 0,
            "99.500000" : 0,
            "99.900000" : 0,
            "99.950000" : 0,
            "99.990000" : 0
          }
        },
        "total_ios" : 0
      },
      "job_runtime" : 60000,
      "usr_cpu" : 12.246667,
      "sys_cpu" : 51.666667,
      "ctx" : 386832,
      "majf" : 0,
      "minf" : 22,
      "iodepth_level" : {
        "1" : 0.100000,
        "2" : 0.100000,
        "4" : 0.100000,
        "8" : 99.999785,
        "16" : 0.000000,
        "32" : 0.000000,
        ">=64" : 0.000000
      },
      "iodepth_submit" : {
        "0" : 0.000000,
        "4" : 100.000000,
        "8" : 0.000000,
        "16" : 0.000000,
        "32" : 0.000000,
        "64" : 0.000000,
        ">=64" : 0.000000
      },
      "iodepth_complete" : {
        "0" : 0.000000,
        "4" : 99.999969,
        "8" : 0.000000,
        "16" : 0.100000,
        "32" : 0.000000,
        "64" : 0.000000,
        ">=64" : 0.000000
      },
      "latency_ns" : {
        "2" : 0.000000,
        "4" : 0.000000,
        "10" : 0.000000,
        "20" : 0.000000,
        "50" : 0.000000,
        "100" : 0.000000,
        "250" : 0.000000,
        "500" : 0.000000,
        "750" : 0.000000,
        "1000" : 0.000000
      },
      "latency_us" : {
        "2" : 0.000000,
        "4" : 0.000000,
        "10" : 0.000000,
        "20" : 0.010000,
        "50" : 0.027034,
        "100" : 36.915855,
        "250" : 58.273480,
        "500" : 1.457921,
        "750" : 0.366523,
        "1000" : 0.200081
      },
      "latency_ms" : {
        "2" : 1.383547,
        "4" : 1.283676,
        "10" : 0.091178,
        "20" : 0.010000,
        "50" : 0.010000,
        "100" : 0.000000,
        "250" : 0.000000,
        "500" : 0.000000,
        "750" : 0.000000,
        "1000" : 0.000000,
        "2000" : 0.000000,
        ">=2000" : 0.000000
      },
      "latency_depth" : 10,
      "latency_target" : 0,
      "latency_percentile" : 100.000000,
      "latency_window" : 0
    },
    {
      "jobname" : "seqread",
      "groupid" : 0,
      "error" : 0,
      "eta" : 0,
      "elapsed" : 61,
      "job options" : {
        "rate" : "80m",
        "rw" : "read",
        "bs" : "1m"
      },
      "read" : {
        "io_bytes" : 5034213376,
        "io_kbytes" : 4916224,
        "bw_bytes" : 83899361,
        "bw" : 81932,
        "iops" : 80.012666,
        "runtime" : 60003,
        "total_ios" : 4801,
        "short_ios" : 0,
        "drop_ios" : 0,
        "slat_ns" : {
          "min" : 36318,
          "max" : 662654,
          "mean" : 93050.304312,
          "stddev" : 34877.225878
        },
        "clat_ns" : {
          "min" : 927143,
          "max" : 13720460,
          "mean" : 1654940.039783,
          "stddev" : 1072717.276358,
          "percentile" : {
            "1.000000" : 1003520,
            "5.000000" : 1044480,
            "10.000000" : 1073152,
            "20.000000" : 1138688,
            "30.000000" : 1204224,
            "40.000000" : 1253376,
            "50.000000" : 1302528,
            "60.000000" : 1368064,
            "70.000000" : 1466368,
            "80.000000" : 1630208,
            "90.000000" : 3063808,
            "95.000000" : 3883008,
            "99.000000" : 5668864,
            "99.500000" : 6258688,
            "99.900000" : 12255232,
            "99.950000" : 12910592,
            "99.990000" : 13697024
          }
        },
        "lat_ns" : {
          "min" : 987136,
          "max" : 13864892,
          "mean" : 1749869.105811,
          "stddev" : 1082021.809857
        },
        "bw_min" : 81756,
        "bw_max" : 81920,
        "bw_agg" : 41.734573,
        "bw_mean" : 81914.533333,
        "bw_dev" : 29.562335,
        "bw_samples" : 120,
        "iops_min" : 79,
        "iops_max" : 80,
        "iops_mean" : 79.966667,
        "iops_stddev" : 0.180258,
        "iops_samples" : 120
      },
      "write" : {
        "io_bytes" : 0,
        "io_kbytes" : 0,
        "bw_bytes" : 0,
        "bw" : 0,
        "iops" : 0.000000,
        "runtime" : 0,
        "total_ios" : 0,
        "short_ios" : 0,
        "drop_ios" : 0,
        "slat_ns" : {
          "min" : 0,
          "max" : 0,
          "mean" : 0.000000,
          "stddev" : 0.000000
        },
        "clat_ns" : {
          "min" : 0,
          "max" : 0,
          "mean" : 0.000000,
          "stddev" : 0.000000,
          "percentile" : {
            "1.000000" : 0,
            "5.000000" : 0,
            "10.000000" : 0,
            "20.000000" : 0,
            "30.000000" : 0,
            "40.000000" : 0,
            "50.000000" : 0,
            "60.000000" : 0,
            "70.000000" : 0,
            "80.000000" : 0,
            "90.000000" : 0,
            "95.000000" : 0,
            "99.000000" : 0,
            "99.500000" : 0,
            "99.900000" : 0,
            "99.950000" : 0,
            "99.990000" : 0
          }
        },
        "lat_ns" : {
          "min" : 0,
          "max" : 0,
          "mean" : 0.000000,
          "stddev" : 0.000000
        },
        "bw_min" : 0,
        "bw_max" : 0,
        "bw_agg" : 0.000000,
        "bw_mean" : 0.000000,
        "bw_dev" : 0.000000,
        "bw_samples" : 0,
        "iops_min" : 0,
        "iops_max" : 0,
        "iops_mean" : 0.000000,
        "iops_stddev" : 0.000000,
        "iops_samples" : 0
      },
      "trim" : {
        "io_bytes" : 0,
        "io_kbytes" : 0,
        "bw_bytes" : 0,
        "bw" : 0,
        "iops" : 0.000000,
        "runtime" : 0,
        "total_ios" : 0,
        "short_ios" : 0,
        "drop_ios" : 0,
        "slat_ns" : {
          "min" : 0,
          "max" : 0,
          "mean" : 0.000000,
          "stddev" : 0.000000
        },
        "clat_ns" : {
          "min" : 0,
          "max" : 0,
          "mean" : 0.000000,
          "stddev" : 0.000000,
          "percentile" : {
            "1.000000" : 0,
            "5.000000" : 0,
            "10.000000" : 0,
            "20.000000" : 0,
            "30.000000" : 0,
            "40.000000" : 0,
            "50.000000" : 0,
            "60.000000" : 0,
            "70.000000" : 0,
            "80.000000" : 0,
            "90.000000" : 0,
            "95.000000" : 0,
            "99.000000" : 0,
            "99.500000" : 0,
            "99.900000" : 0,
            "99.950000" : 0,
            "99.990000" : 0
          }
        },
        "lat_ns" : {
          "min" : 0,
          "max" : 0,
          "mean" : 0.000000,
          "stddev" : 0.000000
        },
        "bw_min" : 0,
        "bw_max" : 0,
        "bw_agg" : 0.000000,
        "bw_mean" : 0.000000,
        "bw_dev" : 0.000000,
        "bw_samples" : 0,
        "iops_min" : 0,
        "iops_max" : 0,
        "iops_mean" : 0.000000,
        "iops_stddev" : 0.000000,
        "iops_samples" : 0
      },
      "sync" : {
        "lat_ns" : {
          "min" : 0,
          "max" : 0,
          "mean" : 0.000000,
          "stddev" : 0.000000,
          "percentile" : {
            "1.000000" : 0,
            "5.000000" : 0,
            "10.000000" : 0,
            "20.000000" : 0,
            "30.000000" : 0,
            "40.000000" : 0,
            "50.000000" : 0,
            "60.000000" : 0,
            "70.000000" : 0,
            "80.000000" : 0,
            "90.000000" : 0,
            "95.000000" : 0,
            "99.000000" : 0,
            "99.500000" : 0,
            "99.900000" : 0,
            "99.950000" : 0,
            "99.990000" : 0
          }
        },
        "total_ios" : 0
      },
      "job_runtime" : 60002,
      "usr_cpu" : 0.133329,
      "sys_cpu" : 1.019966,
      "ctx" : 9595,
      "majf" : 0,
      "minf" : 2570,
      "iodepth_level" : {
        "1" : 99.791710,
        "2" : 0.100000,
        "4" : 0.100000,
        "8" : 0.100000,
        "16" : 0.000000,
        "32" : 0.000000,
        ">=64" : 0.000000
      },
      "iodepth_submit" : {
        "0" : 0.000000,
        "4" : 100.000000,
        "8" : 0.000000,
        "16" : 0.000000,
        "32" : 0.000000,
        "64" : 0.000000,
        ">=64" : 0.000000
      },
      "iodepth_complete" : {
        "0" : 0.000000,
        "4" : 100.000000,
        "8" : 0.000000,
        "16" : 0.000000,
        "32" : 0.000000,
        "64" : 0.000000,
        ">=64" : 0.000000
      },
      "latency_ns" : {
        "2" : 0.000000,
        "4" : 0.000000,
        "10" : 0.000000,
        "20" : 0.000000,
        "50" : 0.000000,
        "100" : 0.000000,
        "250" : 0.000000,
        "500" : 0.000000,
        "750" : 0.000000,
        "1000" : 0.000000
      },
      "latency_us" : {
        "2" : 0.000000,
        "4" : 0.000000,
        "10" : 0.000000,
        "20" : 0.000000,
        "50" : 0.000000,
        "100" : 0.000000,
        "250" : 0.000000,
        "500" : 0.000000,
        "750" : 0.000000,
        "1000" : 0.687357
      },
      "latency_ms" : {
        "2" : 85.523849,
        "4" : 9.206415,
        "10" : 4.394918,
        "20" : 0.187461,
        "50" : 0.000000,
        "100" : 0.000000,
        "250" : 0.000000,
        "500" : 0.000000,
        "750" : 0.000000,
        "1000" : 0.000000,
        "2000" : 0.000000,
        ">=2000" : 0.000000
      },
      "latency_depth" : 10,
      "latency_target" : 0,
      "latency_percentile" : 100.000000,
      "latency_window" : 0
    },
    {
      "jobname" : "seqwrite",
      "groupid" : 0,
      "error" : 0,
      "eta" : 0,
      "elapsed" : 61,
      "job options" : {
        "rate" : "80m",
        "rw" : "write",
        "bs" : "1m"
      },
      "read" : {
        "io_bytes" : 0,
        "io_kbytes" : 0,
        "bw_bytes" : 0,
        "bw" : 0,
        "iops" : 0.000000,
        "runtime" : 0,
        "total_ios" : 0,
        "short_ios" : 0,
        "drop_ios" : 0,
        "slat_ns" : {
          "min" : 0,
          "max" : 0,
          "mean" : 0.000000,
          "stddev" : 0.000000
        },
        "clat_ns" : {
          "min" : 0,
          "max" : 0,
          "mean" : 0.000000,
          "stddev" : 0.000000,
          "percentile" : {
            "1.000000" : 0,
            "5.000000" : 0,
            "10.000000" : 0,
            "20.000000" : 0,
            "30.000000" : 0,
            "40.000000" : 0,
            "50.000000" : 0,
            "60.000000" : 0,
            "70.000000" : 0,
            "80.000000" : 0,
            "90.000000" : 0,
            "95.000000" : 0,
            "99.000000" : 0,
            "99.500000" : 0,
            "99.900000" : 0,
            "99.950000" : 0,
            "99.990000" : 0
          }
        },
        "lat_ns" : {
          "min" : 0,
          "max" : 0,
          "mean" : 0.000000,
          "stddev" : 0.000000
        },
        "bw_min" : 0,
        "bw_max" : 0,
        "bw_agg" : 0.000000,
        "bw_mean" : 0.000000,
        "bw_dev" : 0.000000,
        "bw_samples" : 0,
        "iops_min" : 0,
        "iops_max" : 0,
        "iops_mean" : 0.000000,
        "iops_stddev" : 0.000000,
        "iops_samples" : 0
      },
      "write" : {
        "io_bytes" : 5034213376,
        "io_kbytes" : 4916224,
        "bw_bytes" : 83900759,
        "bw" : 81934,
        "iops" : 80.014000,
        "runtime" : 60002,
        "total_ios" : 4801,
        "short_ios" : 0,
        "drop_ios" : 0,
        "slat_ns" : {
          "min" : 35270,
          "max" : 327975,
          "mean" : 94060.923974,
          "stddev" : 29427.021797
        },
        "clat_ns" : {
          "min" : 386013,
          "max" : 16540231,
          "mean" : 462402.627578,
          "stddev" : 557034.956088,
          "percentile" : {
            "1.000000" : 395264,
            "5.000000" : 399360,
            "10.000000" : 403456,
            "20.000000" : 407552,
            "30.000000" : 415744,
            "40.000000" : 423936,
            "50.000000" : 436224,
            "60.000000" : 440320,
            "70.000000" : 444416,
            "80.000000" : 452608,
            "90.000000" : 468992,
            "95.000000" : 481280,
            "99.000000" : 509952,
            "99.500000" : 585728,
            "99.900000" : 11599872,
            "99.950000" : 13828096,
            "99.990000" : 16580608
          }
        },
        "lat_ns" : {
          "min" : 430501,
          "max" : 16650231,
          "mean" : 558339.252864,
          "stddev" : 558464.418288
        },
        "bw_min" : 79872,
        "bw_max" : 83968,
        "bw_agg" : 99.974370,
        "bw_mean" : 81913.000000,
        "bw_dev" : 904.507369,
        "bw_samples" : 120,
        "iops_min" : 78,
        "iops_max" : 82,
        "iops_mean" : 79.958333,
        "iops_stddev" : 0.823967,
        "iops_samples" : 120
      },
      "trim" : {
        "io_bytes" : 0,
        "io_kbytes" : 0,
        "bw_bytes" : 0,
        "bw" : 0,
        "iops" : 0.000000,
        "runtime" : 0,
        "total_ios" : 0,
        "short_ios" : 0,
        "drop_ios" : 0,
        "slat_ns" : {
          "min" : 0,
          "max" : 0,
          "mean" : 0.000000,
          "stddev" : 0.000000
        },
        "clat_ns" : {
          "min" : 0,
          "max" : 0,
          "mean" : 0.000000,
          "stddev" : 0.000000,
          "percentile" : {
            "1.000000" : 0,
            "5.000000" : 0,
            "10.000000" : 0,
            "20.000000" : 0,
            "30.000000" : 0,
            "40.000000" : 0,
            "50.000000" : 0,
            "60.000000" : 0,
            "70.000000" : 0,
            "80.000000" : 0,
            "90.000000" : 0,
            "95.000000" : 0,
            "99.000000" : 0,
            "99.500000" : 0,
            "99.900000" : 0,
            "99.950000" : 0,
            "99.990000" : 0
          }
        },
        "lat_ns" : {
          "min" : 0,
          "max" : 0,
          "mean" : 0.000000,
          "stddev" : 0.000000
        },
        "bw_min" : 0,
        "bw_max" : 0,
        "bw_agg" : 0.000000,
        "bw_mean" : 0.000000,
        "bw_dev" : 0.000000,
        "bw_samples" : 0,
        "iops_min" : 0,
        "iops_max" : 0,
        "iops_mean" : 0.000000,
        "iops_stddev" : 0.000000,
        "iops_samples" : 0
      },
      "sync" : {
        "lat_ns" : {
          "min" : 0,
          "max" : 0,
          "mean" : 0.000000,
          "stddev" : 0.000000,
          "percentile" : {
            "1.000000" : 0,
            "5.000000" : 0,
            "10.000000" : 0,
            "20.000000" : 0,
            "30.000000" : 0,
            "40.000000" : 0,
            "50.000000" : 0,
            "60.000000" : 0,
            "70.000000" : 0,
            "80.000000" : 0,
            "90.000000" : 0,
            "95.000000" : 0,
            "99.000000" : 0,
            "99.500000" : 0,
            "99.900000" : 0,
            "99.950000" : 0,
            "99.990000" : 0
          }
        },
        "total_ios" : 0
      },
      "job_runtime" : 60001,
      "usr_cpu" : 0.326661,
      "sys_cpu" : 0.819986,
      "ctx" : 9596,
      "majf" : 0,
      "minf" : 12,
      "iodepth_level" : {
        "1" : 99.791710,
        "2" : 0.100000,
        "4" : 0.100000,
        "8" : 0.100000,
        "16" : 0.000000,
        "32" : 0.000000,
        ">=64" : 0.000000
      },
      "iodepth_submit" : {
        "0" : 0.000000,
        "4" : 100.000000,
        "8" : 0.000000,
        "16" : 0.000000,
        "32" : 0.000000,
        "64" : 0.000000,
        ">=64" : 0.000000
      },
      "iodepth_complete" : {
        "0" : 0.000000,
        "4" : 100.000000,
        "8" : 0.000000,
        "16" : 0.000000,
        "32" : 0.000000,
        "64" : 0.000000,
        ">=64" : 0.000000
      },
      "latency_ns" : {
        "2" : 0.000000,
        "4" : 0.000000,
        "10" : 0.000000,
        "20" : 0.000000,
        "50" : 0.000000,
        "100" : 0.000000,
        "250" : 0.000000,
        "500" : 0.000000,
        "750" : 0.000000,
        "1000" : 0.000000
      },
      "latency_us" : {
        "2" : 0.000000,
        "4" : 0.000000,
        "10" : 0.000000,
        "20" : 0.000000,
        "50" : 0.000000,
        "100" : 0.000000,
        "250" : 0.000000,
        "500" : 98.604457,
        "750" : 1.103937,
        "1000" : 0.000000
      },
      "latency_ms" : {
        "2" : 0.000000,
        "4" : 0.041658,
        "10" : 0.104145,
        "20" : 0.145803,
        "50" : 0.000000,
        "100" : 0.000000,
        "250" : 0.000000,
        "500" : 0.000000,
        "750" : 0.000000,
        "1000" : 0.000000,
        "2000" : 0.000000,
        ">=2000" : 0.000000
      },
      "latency_depth" : 10,
      "latency_target" : 0,
      "latency_percentile" : 100.000000,
      "latency_window" : 0
    }
  ],
  "disk_util" : [
    {
      "name" : "nvme0n1",
      "read_ios" : 3252885,
      "write_ios" : 4842,
      "read_merges" : 0,
      "write_merges" : 0,
      "read_ticks" : 499944,
      "write_ticks" : 2360,
      "in_queue" : 502800,
      "util" : 99.846534
    }
  ]
}
